linuxmole/__init__.py
linuxmole/__main__.py
linuxmole/cli.py
linuxmole/config.py
linuxmole/constants.py
linuxmole/helpers.py
linuxmole/interactive.py
linuxmole/logging_setup.py
linuxmole/output.py
linuxmole/plans.py
linuxmole/commands/__init__.py
linuxmole/commands/_helpers.py
linuxmole/commands/analyze.py
linuxmole/commands/clean.py
linuxmole/commands/config_cmd.py
linuxmole/commands/installer.py
linuxmole/commands/optimize.py
linuxmole/commands/purge.py
linuxmole/commands/status.py
linuxmole/commands/uninstall.py
linuxmole/commands/whitelist.py
linuxmole/docker/__init__.py
linuxmole/docker/formatting.py
linuxmole/docker/inspect.py
linuxmole/docker/logs.py
linuxmole/system/__init__.py
linuxmole/system/apt.py
linuxmole/system/metrics.py
linuxmole/system/paths.py
linuxmole-1.2.0.dist-info/licenses/LICENSE
linuxmole-1.2.0.dist-info/METADATA
linuxmole-1.2.0.dist-info/WHEEL
linuxmole-1.2.0.dist-info/entry_points.txt
linuxmole-1.2.0.dist-info/top_level.txt
linuxmole-1.2.0.dist-info/RECORD
