Metadata-Version: 2.4
Name: linuxmole
Version: 1.2.0
Summary: Safe, Mole-inspired maintenance for Linux + Docker.
Author-email: "Andrés Lorente (@4ndymcfly)" <info@hackingepico.com>
License: MIT License
Project-URL: Homepage, https://github.com/4ndymcfly/linux-mole
Project-URL: Repository, https://github.com/4ndymcfly/linux-mole
Project-URL: Issues, https://github.com/4ndymcfly/linux-mole/issues
Keywords: linux,docker,cleanup,maintenance,disk-space,cli,system-tools,devops,server,python
Classifier: License :: OSI Approved :: MIT License
Classifier: Programming Language :: Python :: 3
Classifier: Programming Language :: Python :: 3.8
Classifier: Programming Language :: Python :: 3.9
Classifier: Programming Language :: Python :: 3.10
Classifier: Programming Language :: Python :: 3.11
Classifier: Programming Language :: Python :: 3.12
Classifier: Operating System :: POSIX :: Linux
Classifier: Environment :: Console
Classifier: Topic :: System :: Systems Administration
Requires-Python: >=3.8
License-File: LICENSE
Requires-Dist: rich>=13.0.0
Requires-Dist: textual>=0.47.0
Requires-Dist: tomli>=2.0.0; python_version < "3.11"
Provides-Extra: dev
Requires-Dist: pytest>=7.0.0; extra == "dev"
Requires-Dist: pytest-cov>=4.0.0; extra == "dev"
Requires-Dist: pytest-mock>=3.10.0; extra == "dev"
Dynamic: license-file
